{
  "Parameters": {
    "ProjectName": {
      "Type": "String"
    }
  },
  "Resources": {
    "TASKROLEA2089027": {
      "Type": "AWS::IAM::Role",
      "Properties": {
        "AssumeRolePolicyDocument": {
          "Statement": [
            {
              "Action": "sts:AssumeRole",
              "Effect": "Allow",
              "Principal": {
                "Service": "ecs-tasks.amazonaws.com"
              }
            }
          ],
          "Version": "2012-10-17"
        },
        "ManagedPolicyArns": [
          {
            "Fn::Join": [
              "",
              [
                "arn:",
                {
                  "Ref": "AWS::Partition"
                },
                ":iam::aws:policy/AmazonS3FullAccess"
              ]
            ]
          },
          {
            "Fn::Join": [
              "",
              [
                "arn:",
                {
                  "Ref": "AWS::Partition"
                },
                ":iam::aws:policy/AmazonECS_FullAccess"
              ]
            ]
          }
        ]
      },
      "Metadata": {
        "aws:cdk:path": "DeploymentStack/TASKROLE/Resource"
      }
    },
    "DBSECRETE6F61AC6": {
      "Type": "AWS::SecretsManager::Secret",
      "Properties": {
        "GenerateSecretString": {
          "ExcludePunctuation": true,
          "PasswordLength": 20
        },
        "Name": "dbPassword"
      },
      "Metadata": {
        "aws:cdk:path": "DeploymentStack/DBSECRET/Resource"
      }
    },
    "ARTIFACTBUCKET3AC4D6FF": {
      "Type": "AWS::S3::Bucket",
      "Properties": {
        "BucketName": {
          "Fn::Join": [
            "",
            [
              {
                "Ref": "ProjectName"
              },
              "-artifacts-",
              {
                "Ref": "AWS::AccountId"
              }
            ]
          ]
        },
        "PublicAccessBlockConfiguration": {
          "BlockPublicAcls": true,
          "BlockPublicPolicy": true,
          "IgnorePublicAcls": true,
          "RestrictPublicBuckets": true
        }
      },
      "UpdateReplacePolicy": "Delete",
      "DeletionPolicy": "Delete",
      "Metadata": {
        "aws:cdk:path": "DeploymentStack/ARTIFACTBUCKET/Resource"
      }
    },
    "SGRDS8D02E925": {
      "Type": "AWS::EC2::SecurityGroup",
      "Properties": {
        "GroupDescription": "DeploymentStack/SGRDS",
        "GroupName": "sg_rds",
        "SecurityGroupEgress": [
          {
            "CidrIp": "0.0.0.0/0",
            "Description": "Allow all outbound traffic by default",
            "IpProtocol": "-1"
          }
        ],
        "SecurityGroupIngress": [
          {
            "CidrIp": "10.206.192.0/19",
            "Description": "from 10.206.192.0/19:3306",
            "FromPort": 3306,
            "IpProtocol": "tcp",
            "ToPort": 3306
          }
        ],
        "VpcId": "vpc-03076add1b1efca31"
      },
      "Metadata": {
        "aws:cdk:path": "DeploymentStack/SGRDS/Resource"
      }
    },
    "MYSQLSubnetGroup5B5FBC17": {
      "Type": "AWS::RDS::DBSubnetGroup",
      "Properties": {
        "DBSubnetGroupDescription": "Subnet group for MYSQL database",
        "SubnetIds": [
          "subnet-0615a20c4235b6eea",
          "subnet-06517a5e6a39cda2d"
        ]
      },
      "Metadata": {
        "aws:cdk:path": "DeploymentStack/MYSQL/SubnetGroup/Default"
      }
    },
    "MYSQLDA998D0F": {
      "Type": "AWS::RDS::DBInstance",
      "Properties": {
        "DBInstanceClass": "db.t2.small",
        "AllocatedStorage": "100",
        "CopyTagsToSnapshot": true,
        "DBName": "mlflowdb",
        "DBSubnetGroupName": {
          "Ref": "MYSQLSubnetGroup5B5FBC17"
        },
        "DeletionProtection": false,
        "Engine": "mysql",
        "EngineVersion": "8.0.19",
        "MasterUsername": "master",
        "MasterUserPassword": {
          "Fn::Join": [
            "",
            [
              "{{resolve:secretsmanager:",
              {
                "Ref": "DBSECRETE6F61AC6"
              },
              ":SecretString:::}}"
            ]
          ]
        },
        "Port": "3306",
        "PubliclyAccessible": false,
        "StorageType": "gp2",
        "VPCSecurityGroups": [
          {
            "Fn::GetAtt": [
              "SGRDS8D02E925",
              "GroupId"
            ]
          }
        ]
      },
      "UpdateReplacePolicy": "Delete",
      "DeletionPolicy": "Delete",
      "Metadata": {
        "aws:cdk:path": "DeploymentStack/MYSQL/Resource"
      }
    },
    "CLUSTERCDDEBBE4": {
      "Type": "AWS::ECS::Cluster",
      "Properties": {
        "ClusterName": "mlflow"
      },
      "Metadata": {
        "aws:cdk:path": "DeploymentStack/CLUSTER/Resource"
      }
    },
    "MLflowDDA9BA68": {
      "Type": "AWS::ECS::TaskDefinition",
      "Properties": {
        "ContainerDefinitions": [
          {
            "Environment": [
              {
                "Name": "BUCKET",
                "Value": {
                  "Fn::Join": [
                    "",
                    [
                      "s3://",
                      {
                        "Ref": "ARTIFACTBUCKET3AC4D6FF"
                      }
                    ]
                  ]
                }
              },
              {
                "Name": "HOST",
                "Value": {
                  "Fn::GetAtt": [
                    "MYSQLDA998D0F",
                    "Endpoint.Address"
                  ]
                }
              },
              {
                "Name": "PORT",
                "Value": "3306"
              },
              {
                "Name": "DATABASE",
                "Value": "mlflowdb"
              },
              {
                "Name": "USERNAME",
                "Value": "master"
              }
            ],
            "Essential": true,
            "Image": {
              "Fn::Join": [
                "",
                [
                  "601883093460.dkr.ecr.eu-central-1.",
                  {
                    "Ref": "AWS::URLSuffix"
                  },
                  "/mlflow-containers:1349471251a9ca9c023c33d8c8b86e3d07a592c19e556f33f6d0400062fc8995"
                ]
              ]
            },
            "Name": "Container",
            "PortMappings": [
              {
                "ContainerPort": 5000,
                "HostPort": 5000,
                "Protocol": "tcp"
              }
            ],
            "Secrets": [
              {
                "Name": "PASSWORD",
                "ValueFrom": {
                  "Ref": "DBSECRETE6F61AC6"
                }
              }
            ]
          }
        ],
        "Cpu": "256",
        "ExecutionRoleArn": {
          "Fn::GetAtt": [
            "MLflowExecutionRoleB8ECF96D",
            "Arn"
          ]
        },
        "Family": "DeploymentStackMLflow75B51616",
        "Memory": "512",
        "NetworkMode": "awsvpc",
        "RequiresCompatibilities": [
          "FARGATE"
        ],
        "TaskRoleArn": {
          "Fn::GetAtt": [
            "TASKROLEA2089027",
            "Arn"
          ]
        }
      },
      "Metadata": {
        "aws:cdk:path": "DeploymentStack/MLflow/Resource"
      }
    },
    "MLflowExecutionRoleB8ECF96D": {
      "Type": "AWS::IAM::Role",
      "Properties": {
        "AssumeRolePolicyDocument": {
          "Statement": [
            {
              "Action": "sts:AssumeRole",
              "Effect": "Allow",
              "Principal": {
                "Service": "ecs-tasks.amazonaws.com"
              }
            }
          ],
          "Version": "2012-10-17"
        }
      },
      "Metadata": {
        "aws:cdk:path": "DeploymentStack/MLflow/ExecutionRole/Resource"
      }
    },
    "MLflowExecutionRoleDefaultPolicy23CB19EA": {
      "Type": "AWS::IAM::Policy",
      "Properties": {
        "PolicyDocument": {
          "Statement": [
            {
              "Action": [
                "ecr:BatchCheckLayerAvailability",
                "ecr:GetDownloadUrlForLayer",
                "ecr:BatchGetImage"
              ],
              "Effect": "Allow",
              "Resource": {
                "Fn::Join": [
                  "",
                  [
                    "arn:",
                    {
                      "Ref": "AWS::Partition"
                    },
                    ":ecr:eu-central-1:601883093460:repository/mlflow-containers"
                  ]
                ]
              }
            },
            {
              "Action": "ecr:GetAuthorizationToken",
              "Effect": "Allow",
              "Resource": "*"
            },
            {
              "Action": [
                "secretsmanager:GetSecretValue",
                "secretsmanager:DescribeSecret"
              ],
              "Effect": "Allow",
              "Resource": {
                "Ref": "DBSECRETE6F61AC6"
              }
            }
          ],
          "Version": "2012-10-17"
        },
        "PolicyName": "MLflowExecutionRoleDefaultPolicy23CB19EA",
        "Roles": [
          {
            "Ref": "MLflowExecutionRoleB8ECF96D"
          }
        ]
      },
      "Metadata": {
        "aws:cdk:path": "DeploymentStack/MLflow/ExecutionRole/DefaultPolicy/Resource"
      }
    },
    "MLFLOWLB7B85C32A": {
      "Type": "AWS::ElasticLoadBalancingV2::LoadBalancer",
      "Properties": {
        "LoadBalancerAttributes": [
          {
            "Key": "deletion_protection.enabled",
            "Value": "false"
          }
        ],
        "Scheme": "internet-facing",
        "Subnets": [
          "subnet-0f2520b1f33b7bf62",
          "subnet-0fddba16001f4ec75"
        ],
        "Type": "network"
      },
      "Metadata": {
        "aws:cdk:path": "DeploymentStack/MLFLOW/LB/Resource"
      }
    },
    "MLFLOWLBPublicListener92B8F85A": {
      "Type": "AWS::ElasticLoadBalancingV2::Listener",
      "Properties": {
        "DefaultActions": [
          {
            "TargetGroupArn": {
              "Ref": "MLFLOWLBPublicListenerECSGroupFAEEFBE6"
            },
            "Type": "forward"
          }
        ],
        "LoadBalancerArn": {
          "Ref": "MLFLOWLB7B85C32A"
        },
        "Port": 80,
        "Protocol": "TCP"
      },
      "Metadata": {
        "aws:cdk:path": "DeploymentStack/MLFLOW/LB/PublicListener/Resource"
      }
    },
    "MLFLOWLBPublicListenerECSGroupFAEEFBE6": {
      "Type": "AWS::ElasticLoadBalancingV2::TargetGroup",
      "Properties": {
        "Port": 80,
        "Protocol": "TCP",
        "TargetType": "ip",
        "VpcId": "vpc-03076add1b1efca31"
      },
      "Metadata": {
        "aws:cdk:path": "DeploymentStack/MLFLOW/LB/PublicListener/ECSGroup/Resource"
      }
    },
    "MLFLOWServiceFC39EF8E": {
      "Type": "AWS::ECS::Service",
      "Properties": {
        "Cluster": {
          "Ref": "CLUSTERCDDEBBE4"
        },
        "DeploymentConfiguration": {
          "MaximumPercent": 200,
          "MinimumHealthyPercent": 50
        },
        "DesiredCount": 1,
        "EnableECSManagedTags": false,
        "HealthCheckGracePeriodSeconds": 60,
        "LaunchType": "FARGATE",
        "LoadBalancers": [
          {
            "ContainerName": "Container",
            "ContainerPort": 5000,
            "TargetGroupArn": {
              "Ref": "MLFLOWLBPublicListenerECSGroupFAEEFBE6"
            }
          }
        ],
        "NetworkConfiguration": {
          "AwsvpcConfiguration": {
            "AssignPublicIp": "DISABLED",
            "SecurityGroups": [
              {
                "Fn::GetAtt": [
                  "MLFLOWServiceSecurityGroup224B1FDD",
                  "GroupId"
                ]
              }
            ],
            "Subnets": [
              "subnet-0615a20c4235b6eea",
              "subnet-06517a5e6a39cda2d"
            ]
          }
        },
        "ServiceName": "mlflow",
        "TaskDefinition": {
          "Ref": "MLflowDDA9BA68"
        }
      },
      "DependsOn": [
        "MLFLOWLBPublicListenerECSGroupFAEEFBE6",
        "MLFLOWLBPublicListener92B8F85A"
      ],
      "Metadata": {
        "aws:cdk:path": "DeploymentStack/MLFLOW/Service/Service"
      }
    },
    "MLFLOWServiceSecurityGroup224B1FDD": {
      "Type": "AWS::EC2::SecurityGroup",
      "Properties": {
        "GroupDescription": "DeploymentStack/MLFLOW/Service/SecurityGroup",
        "SecurityGroupEgress": [
          {
            "CidrIp": "0.0.0.0/0",
            "Description": "Allow all outbound traffic by default",
            "IpProtocol": "-1"
          }
        ],
        "SecurityGroupIngress": [
          {
            "CidrIp": "10.206.192.0/19",
            "Description": "Allow inbound from VPC for mlflow",
            "FromPort": 5000,
            "IpProtocol": "tcp",
            "ToPort": 5000
          }
        ],
        "VpcId": "vpc-03076add1b1efca31"
      },
      "Metadata": {
        "aws:cdk:path": "DeploymentStack/MLFLOW/Service/SecurityGroup/Resource"
      }
    },
    "MLFLOWServiceTaskCountTarget5798B92F": {
      "Type": "AWS::ApplicationAutoScaling::ScalableTarget",
      "Properties": {
        "MaxCapacity": 2,
        "MinCapacity": 1,
        "ResourceId": {
          "Fn::Join": [
            "",
            [
              "service/",
              {
                "Ref": "CLUSTERCDDEBBE4"
              },
              "/",
              {
                "Fn::GetAtt": [
                  "MLFLOWServiceFC39EF8E",
                  "Name"
                ]
              }
            ]
          ]
        },
        "RoleARN": {
          "Fn::Join": [
            "",
            [
              "arn:",
              {
                "Ref": "AWS::Partition"
              },
              ":iam::601883093460:role/aws-service-role/ecs.application-autoscaling.amazonaws.com/AWSServiceRoleForApplicationAutoScaling_ECSService"
            ]
          ]
        },
        "ScalableDimension": "ecs:service:DesiredCount",
        "ServiceNamespace": "ecs"
      },
      "Metadata": {
        "aws:cdk:path": "DeploymentStack/MLFLOW/Service/TaskCount/Target/Resource"
      }
    },
    "MLFLOWServiceTaskCountTargetAUTOSCALINGE4A5776E": {
      "Type": "AWS::ApplicationAutoScaling::ScalingPolicy",
      "Properties": {
        "PolicyName": "DeploymentStackMLFLOWServiceTaskCountTargetAUTOSCALINGEEA650B6",
        "PolicyType": "TargetTrackingScaling",
        "ScalingTargetId": {
          "Ref": "MLFLOWServiceTaskCountTarget5798B92F"
        },
        "TargetTrackingScalingPolicyConfiguration": {
          "PredefinedMetricSpecification": {
            "PredefinedMetricType": "ECSServiceAverageCPUUtilization"
          },
          "ScaleInCooldown": 60,
          "ScaleOutCooldown": 60,
          "TargetValue": 70
        }
      },
      "Metadata": {
        "aws:cdk:path": "DeploymentStack/MLFLOW/Service/TaskCount/Target/AUTOSCALING/Resource"
      }
    },
    "CDKMetadata": {
      "Type": "AWS::CDK::Metadata",
      "Properties": {
        "Modules": "aws-cdk=1.65.0,@aws-cdk/assets=1.65.0,@aws-cdk/aws-apigateway=1.65.0,@aws-cdk/aws-applicationautoscaling=1.65.0,@aws-cdk/aws-autoscaling=1.65.0,@aws-cdk/aws-autoscaling-common=1.65.0,@aws-cdk/aws-autoscaling-hooktargets=1.65.0,@aws-cdk/aws-batch=1.65.0,@aws-cdk/aws-certificatemanager=1.65.0,@aws-cdk/aws-cloudformation=1.65.0,@aws-cdk/aws-cloudfront=1.65.0,@aws-cdk/aws-cloudwatch=1.65.0,@aws-cdk/aws-codebuild=1.65.0,@aws-cdk/aws-codecommit=1.65.0,@aws-cdk/aws-codeguruprofiler=1.65.0,@aws-cdk/aws-codepipeline=1.65.0,@aws-cdk/aws-cognito=1.65.0,@aws-cdk/aws-ec2=1.65.0,@aws-cdk/aws-ecr=1.65.0,@aws-cdk/aws-ecr-assets=1.65.0,@aws-cdk/aws-ecs=1.65.0,@aws-cdk/aws-ecs-patterns=1.65.0,@aws-cdk/aws-efs=1.65.0,@aws-cdk/aws-elasticloadbalancing=1.65.0,@aws-cdk/aws-elasticloadbalancingv2=1.65.0,@aws-cdk/aws-events=1.65.0,@aws-cdk/aws-events-targets=1.65.0,@aws-cdk/aws-iam=1.65.0,@aws-cdk/aws-kinesis=1.65.0,@aws-cdk/aws-kms=1.65.0,@aws-cdk/aws-lambda=1.65.0,@aws-cdk/aws-logs=1.65.0,@aws-cdk/aws-rds=1.65.0,@aws-cdk/aws-route53=1.65.0,@aws-cdk/aws-route53-targets=1.65.0,@aws-cdk/aws-s3=1.65.0,@aws-cdk/aws-s3-assets=1.65.0,@aws-cdk/aws-sam=1.65.0,@aws-cdk/aws-secretsmanager=1.65.0,@aws-cdk/aws-servicediscovery=1.65.0,@aws-cdk/aws-sns=1.65.0,@aws-cdk/aws-sns-subscriptions=1.65.0,@aws-cdk/aws-sqs=1.65.0,@aws-cdk/aws-ssm=1.65.0,@aws-cdk/aws-stepfunctions=1.65.0,@aws-cdk/cloud-assembly-schema=1.65.0,@aws-cdk/core=1.65.0,@aws-cdk/custom-resources=1.65.0,@aws-cdk/cx-api=1.65.0,@aws-cdk/region-info=1.65.0,jsii-runtime=Python/3.7.4"
      },
      "Metadata": {
        "aws:cdk:path": "DeploymentStack/CDKMetadata/Default"
      }
    }
  },
  "Outputs": {
    "MLFLOWLoadBalancerDNSAEFB7E43": {
      "Value": {
        "Fn::GetAtt": [
          "MLFLOWLB7B85C32A",
          "DNSName"
        ]
      }
    },
    "LoadBalancerDNS": {
      "Value": {
        "Fn::GetAtt": [
          "MLFLOWLB7B85C32A",
          "DNSName"
        ]
      }
    }
  }
}